PDFSNIPPER/__init__.py
PDFSNIPPER/main.py
pdf_snip-0.0.3.dist-info/LICENSE
pdf_snip-0.0.3.dist-info/METADATA
pdf_snip-0.0.3.dist-info/WHEEL
pdf_snip-0.0.3.dist-info/top_level.txt
pdf_snip-0.0.3.dist-info/RECORD
